{
	"response_code": "0",
	"results": [
		{
			"category": "Entertainment: Video Games",
			"type": "multiple",
			"difficulty": "medium",
			"question": "When Halo 3: ODST was unveiled in 2008, it had a different title. What was the game formally called?",
			"correct_answer": "Halo 3: Recon",
			"incorrect_answers": [
				{
					"incorrect_answer": "Halo 3: Helljumpers"
				},
				{
					"incorrect_answer": "Halo 3: Phantom"
				},
				{
					"incorrect_answer": "Halo 3: Guerilla"
				}
			]
		},
		{
			"category": "Entertainment: Video Games",
			"type": "multiple",
			"difficulty": "medium",
			"question": "Killing Floor started as a mod for which Unreal Engine 2 game?",
			"correct_answer": "Unreal Tournament 2004",
			"incorrect_answers": [
				{
					"incorrect_answer": "Deus Ex: Invisible War"
				},
				{
					"incorrect_answer": "Unreal Tournament 3"
				},
				{
					"incorrect_answer": "Postal"
				}
			]
		},
		{
			"category": "Entertainment: Video Games",
			"type": "multiple",
			"difficulty": "medium",
			"question": "How many Chaos Emeralds can you collect in the first Sonic The Hedgehog?",
			"correct_answer": "Six",
			"incorrect_answers": [
				{
					"incorrect_answer": "Seven"
				},
				{
					"incorrect_answer": "Five"
				},
				{
					"incorrect_answer": "Eight"
				}
			]
		},
		{
			"category": "Entertainment: Video Games",
			"type": "multiple",
			"difficulty": "medium",
			"question": "What is the name of the virus that infected New York in Tom Clancy&#039;s The Division?",
			"correct_answer": "Dollar Flu",
			"incorrect_answers": [
				{
					"incorrect_answer": "Ebola"
				},
				{
					"incorrect_answer": "Red Poison"
				},
				{
					"incorrect_answer": "Smallpox"
				}
			]
		},
		{
			"category": "Entertainment: Video Games",
			"type": "multiple",
			"difficulty": "medium",
			"question": "Who was the first jedi that Starkiller had to kill in Star Wars: The Force Unleashed?",
			"correct_answer": "Rahm Kota",
			"incorrect_answers": [
				{
					"incorrect_answer": "Ahsoka Tano"
				},
				{
					"incorrect_answer": "Kazdan Paratus"
				},
				{
					"incorrect_answer": "Kento Marek"
				}
			]
		},
		{
			"category": "Entertainment: Video Games",
			"type": "multiple",
			"difficulty": "medium",
			"question": "What is the name of the currency in the &quot;Animal Crossing&quot; series?",
			"correct_answer": "Bells",
			"incorrect_answers": [
				{
					"incorrect_answer": "Sea Shells"
				},
				{
					"incorrect_answer": "Leaves"
				},
				{
					"incorrect_answer": "Bugs"
				}
			]
		},
		{
			"category": "Entertainment: Video Games",
			"type": "multiple",
			"difficulty": "medium",
			"question": "What is the world&#039;s first video game console?",
			"correct_answer": "Magnavox Odyssey",
			"incorrect_answers": [
				{
					"incorrect_answer": "Coleco Telstar"
				},
				{
					"incorrect_answer": "Nintendo Color TV Game"
				},
				{
					"incorrect_answer": "Atari 2600"
				}
			]
		},
		{
			"category": "Entertainment: Video Games",
			"type": "multiple",
			"difficulty": "medium",
			"question": "The city of Rockport is featured in which of the following video games?",
			"correct_answer": "Need for Speed: Most Wanted (2005)",
			"incorrect_answers": [
				{
					"incorrect_answer": "Infamous 2"
				},
				{
					"incorrect_answer": "Saints Row: The Third"
				},
				{
					"incorrect_answer": "Burnout Revenge"
				}
			]
		},
		{
			"category": "Entertainment: Video Games",
			"type": "multiple",
			"difficulty": "medium",
			"question": "What was the name of the Secret Organization in the Hotline Miami series? ",
			"correct_answer": "50 Blessings",
			"incorrect_answers": [
				{
					"incorrect_answer": "American Blessings"
				},
				{
					"incorrect_answer": "50 Saints"
				},
				{
					"incorrect_answer": "USSR&#039;s Blessings"
				}
			]
		},
		{
			"category": "Entertainment: Video Games",
			"type": "multiple",
			"difficulty": "medium",
			"question": "Which football player is featured on the international cover version of the video game FIFA 16?",
			"correct_answer": "Lionel Messi",
			"incorrect_answers": [
				{
					"incorrect_answer": "Cristiano Ronaldo"
				},
				{
					"incorrect_answer": "Wayne Rooney"
				},
				{
					"incorrect_answer": "David Beckham"
				}
			]
		},
		{
			"category": "Entertainment: Video Games",
			"type": "multiple",
			"difficulty": "medium",
			"question": "In the Kingdom Heart series who provides the english voice for Master Eraqus?",
			"correct_answer": "Mark Hamill",
			"incorrect_answers": [
				{
					"incorrect_answer": "Jason Dohring"
				},
				{
					"incorrect_answer": "Jesse McCartney"
				},
				{
					"incorrect_answer": "Haley Joel Osment"
				}
			]
		},
		{
			"category": "Entertainment: Video Games",
			"type": "multiple",
			"difficulty": "medium",
			"question": "What was the first interactive movie video game?",
			"correct_answer": "Astron Belt",
			"incorrect_answers": [
				{
					"incorrect_answer": "Dragon&#039;s Lair"
				},
				{
					"incorrect_answer": "Cube Quest"
				},
				{
					"incorrect_answer": "M.A.C.H. 3"
				}
			]
		},
		{
			"category": "Entertainment: Video Games",
			"type": "multiple",
			"difficulty": "medium",
			"question": "What is the name of the machine that fails and essentially dooms mankind in the beginning of the first Half-Life game?",
			"correct_answer": "Anti-mass spectrometer",
			"incorrect_answers": [
				{
					"incorrect_answer": "Oscillation generator"
				},
				{
					"incorrect_answer": "Dark fusion reactor"
				},
				{
					"incorrect_answer": "Dark fusion resonator"
				}
			]
		},
		{
			"category": "Entertainment: Video Games",
			"type": "multiple",
			"difficulty": "medium",
			"question": "What two characters from the game Undertale are never in a relationship or not related?",
			"correct_answer": "Frisk &amp; Chara",
			"incorrect_answers": [
				{
					"incorrect_answer": "Sans &amp; Papyrus"
				},
				{
					"incorrect_answer": "Toriel &amp; Asgore"
				},
				{
					"incorrect_answer": "Alphys &amp; Undyne"
				}
			]
		},
		{
			"category": "Entertainment: Video Games",
			"type": "multiple",
			"difficulty": "medium",
			"question": "In Terraria, which of the following items does the Martian Saucer mini-boss NOT drop?",
			"correct_answer": "Drill Containment Unit",
			"incorrect_answers": [
				{
					"incorrect_answer": "Anti-Gravity Hook"
				},
				{
					"incorrect_answer": "Influx Waver"
				},
				{
					"incorrect_answer": "Cosmic Car Key"
				}
			]
		},
		{
			"category": "Entertainment: Video Games",
			"type": "multiple",
			"difficulty": "medium",
			"question": "By how many minutes are you late to work in &quot;Half-Life&quot;?",
			"correct_answer": "30",
			"incorrect_answers": [
				{
					"incorrect_answer": "5"
				},
				{
					"incorrect_answer": "60"
				},
				{
					"incorrect_answer": "15"
				}
			]
		},
		{
			"category": "Entertainment: Video Games",
			"type": "multiple",
			"difficulty": "medium",
			"question": "In Call of Duty: United Offensive, what two soldiers share a name of a video game character?",
			"correct_answer": "Gordon &amp; Freeman",
			"incorrect_answers": [
				{
					"incorrect_answer": "Sam &amp; Fisher"
				},
				{
					"incorrect_answer": "Nathan &amp; Drake"
				},
				{
					"incorrect_answer": "Dig &amp; Dug"
				}
			]
		},
		{
			"category": "Entertainment: Video Games",
			"type": "multiple",
			"difficulty": "medium",
			"question": "In what year were achivements added to Steam?",
			"correct_answer": "2007",
			"incorrect_answers": [
				{
					"incorrect_answer": "2008"
				},
				{
					"incorrect_answer": "2009"
				},
				{
					"incorrect_answer": "2006"
				}
			]
		},
		{
			"category": "Entertainment: Video Games",
			"type": "multiple",
			"difficulty": "medium",
			"question": "What type of genre is the controversial 2015 game &quot;Hatred&quot;?",
			"correct_answer": "Shoot &#039;Em Up",
			"incorrect_answers": [
				{
					"incorrect_answer": "Point &amp; Click"
				},
				{
					"incorrect_answer": "MMORPG"
				},
				{
					"incorrect_answer": "Simulation"
				}
			]
		},
		{
			"category": "Entertainment: Video Games",
			"type": "multiple",
			"difficulty": "medium",
			"question": "What is the full name of the protagonist from the SNES game Clock Tower?",
			"correct_answer": "Jennifer Simpson",
			"incorrect_answers": [
				{
					"incorrect_answer": "Jennifer Barrows"
				},
				{
					"incorrect_answer": "Jennifer Cartwright"
				},
				{
					"incorrect_answer": "Jennifer Maxwell"
				}
			]
		},
		{
			"category": "Entertainment: Video Games",
			"type": "multiple",
			"difficulty": "medium",
			"question": "What name does the little headcrab in &quot;Half Life 2&quot; have?",
			"correct_answer": "Lamarr",
			"incorrect_answers": [
				{
					"incorrect_answer": "Jumperr"
				},
				{
					"incorrect_answer": "Drett"
				},
				{
					"incorrect_answer": "Jerry"
				}
			]
		},
		{
			"category": "Entertainment: Video Games",
			"type": "multiple",
			"difficulty": "medium",
			"question": "Which of these is NOT the name of a team leader in Pok&eacute;mon GO?",
			"correct_answer": "Leif",
			"incorrect_answers": [
				{
					"incorrect_answer": "Blanche"
				},
				{
					"incorrect_answer": "Spark"
				},
				{
					"incorrect_answer": "Candela"
				}
			]
		},
		{
			"category": "Entertainment: Video Games",
			"type": "multiple",
			"difficulty": "medium",
			"question": "Final Fantasy VI was originally released outside Japan under what name?",
			"correct_answer": "Final Fantasy III",
			"incorrect_answers": [
				{
					"incorrect_answer": "Final Fantasy VI"
				},
				{
					"incorrect_answer": "Final Fantasy V"
				},
				{
					"incorrect_answer": "Final Fantasy II"
				}
			]
		},
		{
			"category": "Entertainment: Video Games",
			"type": "multiple",
			"difficulty": "medium",
			"question": "How many times do you fight the Imprisoned in The Legend of Zelda: Skyward Sword?",
			"correct_answer": "3",
			"incorrect_answers": [
				{
					"incorrect_answer": "2"
				},
				{
					"incorrect_answer": "4"
				},
				{
					"incorrect_answer": "5"
				}
			]
		},
		{
			"category": "Entertainment: Video Games",
			"type": "multiple",
			"difficulty": "medium",
			"question": "When was Chapter 1 of the Source Engine mod &quot;Underhell&quot; released?",
			"correct_answer": "September 1st, 2013",
			"incorrect_answers": [
				{
					"incorrect_answer": "March 3rd, 2011"
				},
				{
					"incorrect_answer": "September 12th, 2013"
				},
				{
					"incorrect_answer": "October 2nd, 2012"
				}
			]
		},
		{
			"category": "Entertainment: Video Games",
			"type": "multiple",
			"difficulty": "medium",
			"question": "When was Final Fantasy XV released?",
			"correct_answer": "November 29th, 2016",
			"incorrect_answers": [
				{
					"incorrect_answer": "October 25th, 2016"
				},
				{
					"incorrect_answer": "December 31th, 2016"
				},
				{
					"incorrect_answer": "November 30th, 2016"
				}
			]
		},
		{
			"category": "Entertainment: Video Games",
			"type": "multiple",
			"difficulty": "medium",
			"question": "During the game&#039;s development, what was the first ever created Pok&eacute;mon?",
			"correct_answer": "Rhyhorn",
			"incorrect_answers": [
				{
					"incorrect_answer": "Bulbasaur"
				},
				{
					"incorrect_answer": "Mew"
				},
				{
					"incorrect_answer": "Arceus"
				}
			]
		},
		{
			"category": "Entertainment: Video Games",
			"type": "multiple",
			"difficulty": "medium",
			"question": "What was the first game ever released that ran on the Source engine?",
			"correct_answer": "Counter-Strike: Source",
			"incorrect_answers": [
				{
					"incorrect_answer": "Half-Life 2"
				},
				{
					"incorrect_answer": "Garry&#039;s Mod"
				},
				{
					"incorrect_answer": "Team Fortress 2"
				}
			]
		},
		{
			"category": "Entertainment: Video Games",
			"type": "multiple",
			"difficulty": "medium",
			"question": "Which of these game franchises were made by Namco?",
			"correct_answer": "Tekken",
			"incorrect_answers": [
				{
					"incorrect_answer": "Street Fighter"
				},
				{
					"incorrect_answer": "Mortal Kombat"
				},
				{
					"incorrect_answer": "Dragon Quest"
				}
			]
		},
		{
			"category": "Entertainment: Video Games",
			"type": "multiple",
			"difficulty": "medium",
			"question": "In the Halo series, what fleet was Thel &#039;Vadam supreme commander of before being branded an Arbiter?",
			"correct_answer": "Fleet of Particular Justice",
			"incorrect_answers": [
				{
					"incorrect_answer": "Fleet of Sacred Consecration"
				},
				{
					"incorrect_answer": "Fleet of Furious Redemption"
				},
				{
					"incorrect_answer": "Fleet of Righteous Vigilance"
				}
			]
		},
		{
			"category": "Entertainment: Video Games",
			"type": "multiple",
			"difficulty": "medium",
			"question": "Which of these songs does NOT play during the Ruins segments of the 2015 game &quot;Undertale&quot;?",
			"correct_answer": "Another Medium",
			"incorrect_answers": [
				{
					"incorrect_answer": "Anticipation"
				},
				{
					"incorrect_answer": "Unnecessary Tension"
				},
				{
					"incorrect_answer": "Ruins"
				}
			]
		},
		{
			"category": "Entertainment: Video Games",
			"type": "multiple",
			"difficulty": "medium",
			"question": "Who voices the infamous Citadel Station A.I known as S.H.O.D.A.N, in the System Shock games?",
			"correct_answer": "Terri Brosius",
			"incorrect_answers": [
				{
					"incorrect_answer": " Jennifer Hale"
				},
				{
					"incorrect_answer": "Jenn Taylor"
				},
				{
					"incorrect_answer": "Lori Alan"
				}
			]
		},
		{
			"category": "Entertainment: Video Games",
			"type": "multiple",
			"difficulty": "medium",
			"question": "This weapon in Counter-Strike: Global Offensive does not exist in real life.",
			"correct_answer": "M4A4",
			"incorrect_answers": [
				{
					"incorrect_answer": "AWP"
				},
				{
					"incorrect_answer": "M4A1"
				},
				{
					"incorrect_answer": "MP9"
				}
			]
		},
		{
			"category": "Entertainment: Video Games",
			"type": "multiple",
			"difficulty": "medium",
			"question": "Which of these characters was almost added into Super Smash Bros. Melee, but not included as the game was too far in development?",
			"correct_answer": "Solid Snake",
			"incorrect_answers": [
				{
					"incorrect_answer": "Pit"
				},
				{
					"incorrect_answer": "Meta Knight"
				},
				{
					"incorrect_answer": "R.O.B."
				}
			]
		},
		{
			"category": "Entertainment: Video Games",
			"type": "multiple",
			"difficulty": "medium",
			"question": "The default playermodel of Garry&#039;s Mod is this Half Life 2 character.",
			"correct_answer": "Isaac Kleiner",
			"incorrect_answers": [
				{
					"incorrect_answer": "G-Man"
				},
				{
					"incorrect_answer": "Alyx Vance"
				},
				{
					"incorrect_answer": "Gordon Freeman"
				}
			]
		},
		{
			"category": "Entertainment: Video Games",
			"type": "multiple",
			"difficulty": "medium",
			"question": "What was the name of the protagonist of Metal Gear Solid V: The Phantom Pain?",
			"correct_answer": "Punished &quot;Venom&quot; Snake",
			"incorrect_answers": [
				{
					"incorrect_answer": "Miller"
				},
				{
					"incorrect_answer": "Solid Snake"
				},
				{
					"incorrect_answer": "Ocelot"
				}
			]
		},
		{
			"category": "Entertainment: Video Games",
			"type": "multiple",
			"difficulty": "medium",
			"question": "In The Elder Scrolls V: Skyrim, who is the jester in the dark brotherhood?",
			"correct_answer": "Cicero",
			"incorrect_answers": [
				{
					"incorrect_answer": "Lucien Lachance"
				},
				{
					"incorrect_answer": "Archimedes"
				},
				{
					"incorrect_answer": "Astrid"
				}
			]
		},
		{
			"category": "Entertainment: Video Games",
			"type": "multiple",
			"difficulty": "medium",
			"question": "Phil Fish was the designer of which game?",
			"correct_answer": "Fez",
			"incorrect_answers": [
				{
					"incorrect_answer": "Super Meat Boy"
				},
				{
					"incorrect_answer": "Hotline Miami"
				},
				{
					"incorrect_answer": "FTL"
				}
			]
		},
		{
			"category": "Entertainment: Video Games",
			"type": "multiple",
			"difficulty": "medium",
			"question": "In what year was &quot;Super Mario Sunshine&quot; released?",
			"correct_answer": "2002",
			"incorrect_answers": [
				{
					"incorrect_answer": "2003"
				},
				{
					"incorrect_answer": "2000"
				},
				{
					"incorrect_answer": "2004"
				}
			]
		},
		{
			"category": "Entertainment: Video Games",
			"type": "multiple",
			"difficulty": "medium",
			"question": "What was the original name of  &quot;Minecraft&quot;?",
			"correct_answer": "Cave Game",
			"incorrect_answers": [
				{
					"incorrect_answer": "Minecraft: Order of the Stone"
				},
				{
					"incorrect_answer": "Dig And Build"
				},
				{
					"incorrect_answer": "Infiniminer"
				}
			]
		},
		{
			"category": "Entertainment: Video Games",
			"type": "multiple",
			"difficulty": "medium",
			"question": "What is the real name of the Scout in &quot;Team Fortress 2&quot;?",
			"correct_answer": "Jeremy",
			"incorrect_answers": [
				{
					"incorrect_answer": "Lance"
				},
				{
					"incorrect_answer": "Walter"
				},
				{
					"incorrect_answer": "John"
				}
			]
		},
		{
			"category": "Entertainment: Video Games",
			"type": "multiple",
			"difficulty": "medium",
			"question": "In &quot;The Binding of Isaac&quot;, what is the name of the final boss that you fight in The Void?",
			"correct_answer": "Delirium",
			"incorrect_answers": [
				{
					"incorrect_answer": "Mega Satan"
				},
				{
					"incorrect_answer": "Hush"
				},
				{
					"incorrect_answer": "The Lamb"
				}
			]
		},
		{
			"category": "Entertainment: Video Games",
			"type": "multiple",
			"difficulty": "medium",
			"question": "Which German city does the map &quot;Clubhouse&quot; in &quot;Tom Clancy&#039;s Rainbow Six Siege&quot; take place in?",
			"correct_answer": "Hannover",
			"incorrect_answers": [
				{
					"incorrect_answer": "Berlin"
				},
				{
					"incorrect_answer": "Hamburg"
				},
				{
					"incorrect_answer": "Munich"
				}
			]
		},
		{
			"category": "Entertainment: Video Games",
			"type": "multiple",
			"difficulty": "medium",
			"question": "Which one of these was not a member of the Fiendish Five in the game Sly Cooper and the Thievius Raccoonus?",
			"correct_answer": "Dimitri Lousteau",
			"incorrect_answers": [
				{
					"incorrect_answer": "Mz. Ruby"
				},
				{
					"incorrect_answer": "Muggshot"
				},
				{
					"incorrect_answer": "Clockwerk"
				}
			]
		},
		{
			"category": "Entertainment: Video Games",
			"type": "multiple",
			"difficulty": "medium",
			"question": "In Terraria, which of these items is NOT crafted at a Mythril Anvil?",
			"correct_answer": "Ankh Charm",
			"incorrect_answers": [
				{
					"incorrect_answer": "Venom Staff"
				},
				{
					"incorrect_answer": "Sky Fracture"
				},
				{
					"incorrect_answer": "Orichalcum Tools"
				}
			]
		},
		{
			"category": "Entertainment: Video Games",
			"type": "multiple",
			"difficulty": "medium",
			"question": "What was the first Weapon Pack for Payday 2?",
			"correct_answer": "The Gage Weapon Pack #1",
			"incorrect_answers": [
				{
					"incorrect_answer": "The Overkill Pack"
				},
				{
					"incorrect_answer": "The Gage Chivalry Pack"
				},
				{
					"incorrect_answer": "The Gage Historical Pack"
				}
			]
		},
		{
			"category": "Entertainment: Video Games",
			"type": "multiple",
			"difficulty": "medium",
			"question": "Who is the English voice actor for Sora from the Kingdom Hearts series?",
			"correct_answer": "Haley Joel Osment",
			"incorrect_answers": [
				{
					"incorrect_answer": "Kōki Uchiyama"
				},
				{
					"incorrect_answer": "Jesse McCartney"
				},
				{
					"incorrect_answer": "Miyu Irino"
				}
			]
		},
		{
			"category": "Entertainment: Video Games",
			"type": "multiple",
			"difficulty": "medium",
			"question": "Which of these games was NOT a Nintendo Switch launch title in the United States? ",
			"correct_answer": "Voez",
			"incorrect_answers": [
				{
					"incorrect_answer": "Just Dance 2017"
				},
				{
					"incorrect_answer": "Snipperclips"
				},
				{
					"incorrect_answer": "Fast RMX"
				}
			]
		},
		{
			"category": "Entertainment: Video Games",
			"type": "multiple",
			"difficulty": "medium",
			"question": "Toby Fox&#039;s &quot;Megalovania&quot; was first used where?",
			"correct_answer": "Radiation&#039;s Earthbound Halloween Hack",
			"incorrect_answers": [
				{
					"incorrect_answer": "Homestuck: [S] Wake"
				},
				{
					"incorrect_answer": "Undertale"
				},
				{
					"incorrect_answer": "Mother: Cognitive Dissonance"
				}
			]
		},
		{
			"category": "Entertainment: Video Games",
			"type": "multiple",
			"difficulty": "medium",
			"question": "What is the name of the creature that the main character befriends in &quot;The Last Guardian&quot;?",
			"correct_answer": "Trico",
			"incorrect_answers": [
				{
					"incorrect_answer": "Nico"
				},
				{
					"incorrect_answer": "Wolf"
				},
				{
					"incorrect_answer": "Andazi"
				}
			]
		}
	]
}