{
	"response_code": "0",
	"results": [
		{
			"category": "Entertainment: Comics",
			"type": "multiple",
			"difficulty": "medium",
			"question": "In Marvel Comics, Taurus is the founder and leader of which criminal organization?",
			"correct_answer": "Zodiac",
			"incorrect_answers": [
				"Scorpio"
				,
				"Tiger Mafia"
				,
				"The Union"
				
			]
		},
		{
			"category": "Entertainment: Comics",
			"type": "multiple",
			"difficulty": "medium",
			"question": "What was the name of the first Robin in the Batman comics?",
			"correct_answer": "Dick Grayson",
			"incorrect_answers": [
				"Bruce Wayne"
				,
				"Jason Todd"
				,
				"Tim Drake"
				
			]
		},
		{
			"category": "Entertainment: Comics",
			"type": "multiple",
			"difficulty": "medium",
			"question": "What is the name of the main character in the webcomic Gunnerkrigg Court by Tom Siddell?",
			"correct_answer": "Antimony",
			"incorrect_answers": [
				"Bismuth"
				,
				"Mercury"
				,
				"Cobalt"
				
			]
		},
		{
			"category": "Entertainment: Comics",
			"type": "multiple",
			"difficulty": "medium",
			"question": "In Pre-Super Genesis universe of &quot;Sonic the Hedgehog&quot; comic, what was the name of  Sally Acorn&#039;s brother?",
			"correct_answer": "Elias Acorn",
			"incorrect_answers": [
				"Maximillian Acorn"
				,
				"Alexis Acorn"
				,
				"Frederick Acorn"
				
			]
		},
		{
			"category": "Entertainment: Comics",
			"type": "multiple",
			"difficulty": "medium",
			"question": "Which issue of the &quot;Sonic the Hedgehog&quot; comic did Scourge the Hedgehog make his first appearance?",
			"correct_answer": "Sonic the Hedgehog #11",
			"incorrect_answers": [
				"Sonic Universe #32"
				,
				"Sonic the Hedgehog #161"
				,
				"Sonic the Hedgehog #47"
				
			]
		},
		{
			"category": "Entertainment: Comics",
			"type": "multiple",
			"difficulty": "medium",
			"question": "In &quot;Sonic the Hedgehog&quot; comic, who was the creator of Roboticizer? ",
			"correct_answer": "Professor Charles the Hedgehog",
			"incorrect_answers": [
				"Julian Robotnik"
				,
				"Ivo Robotnik"
				,
				"Snively Robotnik"
				
			]
		},
		{
			"category": "Entertainment: Comics",
			"type": "multiple",
			"difficulty": "medium",
			"question": "Who wrote the Batman comic series &quot;The Killing Joke&quot;?",
			"correct_answer": "Alan Moore",
			"incorrect_answers": [
				"Bill Finger"
				,
				"Frank Miller"
				,
				"Jerry Siegel"
				
			]
		},
		{
			"category": "Entertainment: Comics",
			"type": "multiple",
			"difficulty": "medium",
			"question": "Who authored The Adventures of Tintin?",
			"correct_answer": "Herg&eacute;",
			"incorrect_answers": [
				"E.P. Jacobs"
				,
				"Rin Tin Tin"
				,
				"Chic Young"
				
			]
		},
		{
			"category": "Entertainment: Comics",
			"type": "multiple",
			"difficulty": "medium",
			"question": "Who created Ultron of Earth-616?",
			"correct_answer": "Henry Pym",
			"incorrect_answers": [
				"Amadeus Cho"
				,
				"Tony Stark"
				,
				"Reed Richards"
				
			]
		},
		{
			"category": "Entertainment: Comics",
			"type": "multiple",
			"difficulty": "medium",
			"question": "In the comics, which Sonic character took command of the Dark Legion after Luger&#039;s assassination?",
			"correct_answer": "Lien-Da",
			"incorrect_answers": [
				"Kragok"
				,
				"Dimitri"
				,
				"Remington"
				
			]
		}
	]
}